{
  "indexes": [
    {
      "collectionGroup": "productInventory",
      "queryScope": "COLLECTION",
      "fields": [
        { "fieldPath": "productId", "order": "ASCENDING" },
        { "fieldPath": "receivedAt", "order": "DESCENDING" }
      ]
    },
    {
      "collectionGroup": "productInventory",
      "queryScope": "COLLECTION",
      "fields": [
        { "fieldPath": "productId", "order": "ASCENDING" },
        { "fieldPath": "status", "order": "ASCENDING" },
        { "fieldPath": "receivedAt", "order": "DESCENDING" }
      ]
    },
    {
      "collectionGroup": "productInventory",
      "queryScope": "COLLECTION",
      "fields": [
        { "fieldPath": "storeId", "order": "ASCENDING" },
        { "fieldPath": "productId", "order": "ASCENDING" },
        { "fieldPath": "receivedAt", "order": "DESCENDING" }
      ]
    },
    {
      "collectionGroup": "productInventory",
      "queryScope": "COLLECTION",
      "fields": [
        { "fieldPath": "productId", "order": "ASCENDING" },
        { "fieldPath": "companyId", "order": "ASCENDING" },
        { "fieldPath": "storeId", "order": "ASCENDING" },
        { "fieldPath": "status", "order": "ASCENDING" },
        { "fieldPath": "receivedAt", "order": "ASCENDING" }
      ]
    },
    {
      "collectionGroup": "productInventoryEntries",
      "queryScope": "COLLECTION",
      "fields": [
        { "fieldPath": "productId", "order": "ASCENDING" },
        { "fieldPath": "companyId", "order": "ASCENDING" },
        { "fieldPath": "status", "order": "ASCENDING" },
        { "fieldPath": "receivedAt", "order": "ASCENDING" }
      ]
    },
    {
      "collectionGroup": "productInventoryEntries",
      "queryScope": "COLLECTION",
      "fields": [
        { "fieldPath": "productId", "order": "ASCENDING" },
        { "fieldPath": "companyId", "order": "ASCENDING" },
        { "fieldPath": "receivedAt", "order": "ASCENDING" }
      ]
    },
    {
      "collectionGroup": "productInventoryEntries",
      "queryScope": "COLLECTION",
      "fields": [
        { "fieldPath": "companyId", "order": "ASCENDING" },
        { "fieldPath": "status", "order": "ASCENDING" },
        { "fieldPath": "receivedAt", "order": "ASCENDING" }
      ]
    },
    {
      "collectionGroup": "companyBillingHistory",
      "queryScope": "COLLECTION",
      "fields": [
        {
          "fieldPath": "storeId",
          "order": "ASCENDING"
        },
        {
          "fieldPath": "paidAt",
          "order": "DESCENDING"
        }
      ]
    },
    {
      "collectionGroup": "companyBillingHistory",
      "queryScope": "COLLECTION",
      "fields": [
        {
          "fieldPath": "companyId",
          "order": "ASCENDING"
        },
        {
          "fieldPath": "paidAt",
          "order": "DESCENDING"
        }
      ]
    },
    {
      "collectionGroup": "devices",
      "queryScope": "COLLECTION",
      "fields": [
        {
          "fieldPath": "storeId",
          "order": "ASCENDING"
        },
        {
          "fieldPath": "createdAt",
          "order": "DESCENDING"
        }
      ]
    }
    ,
    {
      "collectionGroup": "customers",
      "queryScope": "COLLECTION",
      "fields": [
        { "fieldPath": "companyId", "order": "ASCENDING" },
        { "fieldPath": "createdAt", "order": "DESCENDING" }
      ]
    },
    {
      "collectionGroup": "customers",
      "queryScope": "COLLECTION",
      "fields": [
        { "fieldPath": "companyId", "order": "ASCENDING" },
        { "fieldPath": "storeId", "order": "ASCENDING" },
        { "fieldPath": "createdAt", "order": "DESCENDING" }
      ]
    }
    ,
    {
      "collectionGroup": "products",
      "queryScope": "COLLECTION",
      "fields": [
        { "fieldPath": "companyId", "order": "ASCENDING" },
        { "fieldPath": "updatedAt", "order": "DESCENDING" }
      ]
    },
    {
      "collectionGroup": "products",
      "queryScope": "COLLECTION",
      "fields": [
        { "fieldPath": "companyId", "order": "ASCENDING" },
        { "fieldPath": "storeId", "order": "ASCENDING" },
        { "fieldPath": "updatedAt", "order": "DESCENDING" }
      ]
    }
    ,
    {
      "collectionGroup": "subscriptions",
      "queryScope": "COLLECTION",
      "fields": [
        { "fieldPath": "companyId", "order": "ASCENDING" },
        { "fieldPath": "storeId", "order": "ASCENDING" },
        { "fieldPath": "endDate", "order": "DESCENDING" }
      ]
    },
    {
      "collectionGroup": "orderSellingTracking",
      "queryScope": "COLLECTION",
      "fields": [
        { "fieldPath": "orderId", "order": "ASCENDING" },
        { "fieldPath": "createdAt", "order": "DESCENDING" }
      ]
    }
    ,
    {
      "collectionGroup": "ordersSellingTracking",
      "queryScope": "COLLECTION",
      "fields": [
        { "fieldPath": "status", "order": "ASCENDING" },
        { "fieldPath": "updatedAt", "order": "DESCENDING" }
      ]
    }
    ,
    {
      "collectionGroup": "orderAccountingLedger",
      "queryScope": "COLLECTION",
      "fields": [
        { "fieldPath": "companyId", "order": "ASCENDING" },
        { "fieldPath": "storeId", "order": "ASCENDING" },
        { "fieldPath": "createdAt", "order": "DESCENDING" }
      ]
    }
    ,
    {
      "collectionGroup": "orderAccountingLedger",
      "queryScope": "COLLECTION",
      "fields": [
        { "fieldPath": "companyId", "order": "ASCENDING" },
        { "fieldPath": "storeId", "order": "ASCENDING" },
        { "fieldPath": "eventType", "order": "ASCENDING" },
        { "fieldPath": "createdAt", "order": "DESCENDING" }
      ]
    },
    {
      "collectionGroup": "orderAccountingLedger",
      "queryScope": "COLLECTION",
      "fields": [
        { "fieldPath": "companyId", "order": "ASCENDING" },
        { "fieldPath": "storeId", "order": "ASCENDING" },
        { "fieldPath": "eventType", "order": "ASCENDING" },
        { "fieldPath": "createdAt", "order": "ASCENDING" }
      ]
    },
    {
      "collectionGroup": "orderAccountingLedger",
      "queryScope": "COLLECTION",
      "fields": [
        { "fieldPath": "companyId", "order": "ASCENDING" },
        { "fieldPath": "eventType", "order": "ASCENDING" },
        { "fieldPath": "createdAt", "order": "ASCENDING" }
      ]
    },
    {
      "collectionGroup": "orderAccountingLedger",
      "queryScope": "COLLECTION",
      "fields": [
        { "fieldPath": "companyId", "order": "ASCENDING" },
        { "fieldPath": "eventType", "order": "ASCENDING" },
        { "fieldPath": "orderId", "order": "ASCENDING" },
        { "fieldPath": "storeId", "order": "ASCENDING" },
        { "fieldPath": "createdAt", "order": "ASCENDING" }
      ]
    },
    {
      "collectionGroup": "productTags",
      "queryScope": "COLLECTION",
      "fields": [
        { "fieldPath": "storeId", "order": "ASCENDING" },
        { "fieldPath": "isActive", "order": "ASCENDING" },
        { "fieldPath": "group", "order": "ASCENDING" },
        { "fieldPath": "createdAt", "order": "ASCENDING" }
      ]
    },
    {
      "collectionGroup": "productTags",
      "queryScope": "COLLECTION",
      "fields": [
        { "fieldPath": "storeId", "order": "ASCENDING" },
        { "fieldPath": "group", "order": "ASCENDING" },
        { "fieldPath": "createdAt", "order": "ASCENDING" }
      ]
    },
    {
      "collectionGroup": "expenseLogs",
      "queryScope": "COLLECTION",
      "fields": [
        { "fieldPath": "storeId", "order": "ASCENDING" },
        { "fieldPath": "paymentDate", "order": "ASCENDING" }
      ]
    },
    {
      "collectionGroup": "orders",
      "queryScope": "COLLECTION",
      "fields": [
        { "fieldPath": "storeId", "order": "ASCENDING" },
        { "fieldPath": "status", "order": "ASCENDING" },
        { "fieldPath": "createdAt", "order": "ASCENDING" }
      ]
    },
    {
      "collectionGroup": "ordersSellingTracking",
      "queryScope": "COLLECTION",
      "fields": [
        { "fieldPath": "status", "order": "ASCENDING" },
        { "fieldPath": "createdAt", "order": "DESCENDING" }
      ]
    },
    {
      "collectionGroup": "ordersSellingTracking",
      "queryScope": "COLLECTION",
      "fields": [
        { "fieldPath": "storeId", "order": "ASCENDING" },
        { "fieldPath": "status", "order": "ASCENDING" },
        { "fieldPath": "createdAt", "order": "ASCENDING" }
      ]
    },
    {
      "collectionGroup": "ordersSellingTracking",
      "queryScope": "COLLECTION",
      "fields": [
        { "fieldPath": "companyId", "order": "ASCENDING" },
        { "fieldPath": "status", "order": "ASCENDING" },
        { "fieldPath": "createdAt", "order": "ASCENDING" }
      ]
    },
    {
      "collectionGroup": "inventoryDeductions",
      "queryScope": "COLLECTION",
      "fields": [
        { "fieldPath": "storeId", "order": "ASCENDING" },
        { "fieldPath": "deductedAt", "order": "DESCENDING" }
      ]
    },
    {
      "collectionGroup": "inventoryDeductions",
      "queryScope": "COLLECTION",
      "fields": [
        { "fieldPath": "companyId", "order": "ASCENDING" },
        { "fieldPath": "deductedAt", "order": "DESCENDING" }
      ]
    },
    {
      "collectionGroup": "inventoryDeductions",
      "queryScope": "COLLECTION",
      "fields": [
        { "fieldPath": "storeId", "order": "ASCENDING" },
        { "fieldPath": "companyId", "order": "ASCENDING" },
        { "fieldPath": "deductedAt", "order": "DESCENDING" }
      ]
    },
    {
      "collectionGroup": "ordersSellingTracking",
      "queryScope": "COLLECTION",
      "fields": [
        { "fieldPath": "storeId", "order": "ASCENDING" },
        { "fieldPath": "createdAt", "order": "DESCENDING" }
      ]
    },
    {
      "collectionGroup": "ordersSellingTracking",
      "queryScope": "COLLECTION",
      "fields": [
        { "fieldPath": "companyId", "order": "ASCENDING" },
        { "fieldPath": "createdAt", "order": "DESCENDING" }
      ]
    },
    {
      "collectionGroup": "ordersSellingTracking",
      "queryScope": "COLLECTION",
      "fields": [
        { "fieldPath": "storeId", "order": "ASCENDING" },
        { "fieldPath": "companyId", "order": "ASCENDING" },
        { "fieldPath": "createdAt", "order": "DESCENDING" }
      ]
    }
  ],
  "fieldOverrides": []
}
